evkc/__init__.py
evkc/__main__.py
evkc/crypto.py
evkc/hardening.py
evkc/manifest.py
evkc/pack.py
evkc/run.py
evkc/sandbox.py
evkc/verify.py
evkc/windows_job.py
evkc-0.1.0.dist-info/licenses/LICENSE
evkc-0.1.0.dist-info/METADATA
evkc-0.1.0.dist-info/WHEEL
evkc-0.1.0.dist-info/entry_points.txt
evkc-0.1.0.dist-info/top_level.txt
evkc-0.1.0.dist-info/RECORD
