Metadata-Version: 2.4
Name: evkc
Version: 0.1.0
Summary: eVKC SCVE minimal toolkit
Author: eVKC
License: Apache License
Project-URL: Homepage, https://github.com/Maverick0351a/sCVE-SelfContainedVerifiableEnvironment
Project-URL: Repository, https://github.com/Maverick0351a/sCVE-SelfContainedVerifiableEnvironment
Project-URL: Issues, https://github.com/Maverick0351a/sCVE-SelfContainedVerifiableEnvironment/issues
Keywords: reproducibility,verification,capsule,ed25519,policy,sandbox
Classifier: Development Status :: 3 - Alpha
Classifier: Intended Audience :: Developers
Classifier: License :: OSI Approved :: Apache Software License
Classifier: Operating System :: Microsoft :: Windows
Classifier: Programming Language :: Python
Classifier: Programming Language :: Python :: 3
Classifier: Programming Language :: Python :: 3 :: Only
Classifier: Programming Language :: Python :: 3.9
Classifier: Programming Language :: Python :: 3.10
Classifier: Programming Language :: Python :: 3.11
Classifier: Topic :: Software Development :: Build Tools
Classifier: Topic :: Security
Requires-Python: >=3.9
License-File: LICENSE
Requires-Dist: pynacl>=1.5.0
Dynamic: license-file
